{
  "Version": "2008-10-17",
  "Statement": [
    {
      "Effect": "Allow",
      "Principal": {
        "AWS": [
          "018250382163",
          "241689241215"
        ]
      },
      "Action": "s3:*",
      "Resource": [
        "arn:aws:s3:::cf-templates-681v3yr6sl6i-us-west-2/*"
      ]
    },
    {
      "Effect": "Deny",
      "Principal": "*",
      "Action": "s3:*",
      "Resource": "arn:aws:s3:::cf-templates-681v3yr6sl6i-us-west-2/*",
      "Condition": {
        "Bool": {
          "aws:SecureTransport": "false"
        }
      }
    }
  ]
}
